{
    "results": [
        {
            "hits": [
                {
                    "fast_ship": {
                        "fast_ship_73": 1
                    },
                    "category": {
                        "category_en": "Eyeglasses"
                    },
                    "f_material": {
                        "f_material_en": [
                            "Plastic"
                        ]
                    },
                    "s_features": {
                        "s_features_73": [
                            "Spring Hinge",
                            "Lightweight"
                        ]
                    },
                    "global": {
                        "name": "Arise Collective Vexley",
                        "category_id": 2,
                        "brand_id": 459,
                        "brand": "Arise Collective",
                        "color_code_id": 696008,
                        "more_color_count": 1,
                        "brand_cn": "Arise Collective",
                        "lessThan8": 1,
                        "image_url": "https://image4.cdnsbg.com/2/459/696008_1733395050212.jpg",
                        "product_id": 213552
                    },
                    "url": {
                        "url_73": "/designer-eyeglasses/Arise-Collective/Arise-Collective-Vexley-DB1713-C5-696008.html"
                    },
                    "outlet": {
                        "outlet_73": 0
                    },
                    "free_lenses": {
                        "73": "1"
                    },
                    "rrp": {
                        "rrp_73": "0.00"
                    },
                    "price_for_clearance": {
                        "price_for_clearance_73": 911900
                    },
                    "bubble": {
                        "bubble_73": 0
                    },
                    "best_price_guarantee": [
                        {
                            "73": 0
                        }
                    ],
                    "s_popular": {
                        "s_popular_73": [
                            "Value Collection",
                            "In Stock",
                            "New Arrivals"
                        ]
                    },
                    "objectID": "GL696008",
                    "_highlightResult": {
                        "global": {
                            "name": {
                                "value": "Arise Collective Vexley",
                                "matchLevel": "none",
                                "matchedWords": []
                            },
                            "brand": {
                                "value": "Arise Collective",
                                "matchLevel": "none",
                                "matchedWords": []
                            }
                        }
                    }
                },
                {
                    "fast_ship": {
                        "fast_ship_73": 1
                    },
                    "category": {
                        "category_en": "Eyeglasses"
                    },
                    "f_material": {
                        "f_material_en": [
                            "Plastic"
                        ]
                    },
                    "s_features": {
                        "s_features_73": [
                            "Lightweight"
                        ]
                    },
                    "global": {
                        "name": "Arise Collective Texan",
                        "category_id": 2,
                        "brand_id": 459,
                        "brand": "Arise Collective",
                        "color_code_id": 696007,
                        "more_color_count": 1,
                        "brand_cn": "Arise Collective",
                        "lessThan8": 1,
                        "image_url": "https://image4.cdnsbg.com/2/459/696007_1733395050212.jpg",
                        "product_id": 213551
                    },
                    "url": {
                        "url_73": "/designer-eyeglasses/Arise-Collective/Arise-Collective-Texan-K949-C1-696007.html"
                    },
                    "outlet": {
                        "outlet_73": 0
                    },
                    "free_lenses": {
                        "73": "1"
                    },
                    "rrp": {
                        "rrp_73": "0.00"
                    },
                    "price_for_clearance": {
                        "price_for_clearance_73": 911900
                    },
                    "bubble": {
                        "bubble_73": 0
                    },
                    "best_price_guarantee": [
                        {
                            "73": 0
                        }
                    ],
                    "s_popular": {
                        "s_popular_73": [
                            "Value Collection",
                            "In Stock",
                            "New Arrivals"
                        ]
                    },
                    "objectID": "GL696007",
                    "_highlightResult": {
                        "global": {
                            "name": {
                                "value": "Arise Collective Texan",
                                "matchLevel": "none",
                                "matchedWords": []
                            },
                            "brand": {
                                "value": "Arise Collective",
                                "matchLevel": "none",
                                "matchedWords": []
                            }
                        }
                    }
                },
                {
                    "fast_ship": {
                        "fast_ship_73": 1
                    },
                    "category": {
                        "category_en": "Eyeglasses"
                    },
                    "f_material": {
                        "f_material_en": [
                            "Plastic"
                        ]
                    },
                    "s_features": {
                        "s_features_73": [
                            "Spring Hinge",
                            "Lightweight"
                        ]
                    },
                    "global": {
                        "name": "Arise Collective Paxton",
                        "category_id": 2,
                        "brand_id": 459,
                        "brand": "Arise Collective",
                        "color_code_id": 696006,
                        "more_color_count": 1,
                        "brand_cn": "Arise Collective",
                        "lessThan8": 1,
                        "image_url": "https://image4.cdnsbg.com/2/459/696006_1733395050211.jpg",
                        "product_id": 213550
                    },
                    "url": {
                        "url_73": "/designer-eyeglasses/Arise-Collective/Arise-Collective-Paxton-K1091D-C2-696006.html"
                    },
                    "outlet": {
                        "outlet_73": 0
                    },
                    "free_lenses": {
                        "73": "1"
                    },
                    "rrp": {
                        "rrp_73": "0.00"
                    },
                    "price_for_clearance": {
                        "price_for_clearance_73": 911900
                    },
                    "bubble": {
                        "bubble_73": 0
                    },
                    "best_price_guarantee": [
                        {
                            "73": 0
                        }
                    ],
                    "s_popular": {
                        "s_popular_73": [
                            "Value Collection",
                            "In Stock",
                            "New Arrivals"
                        ]
                    },
                    "objectID": "GL696006",
                    "_highlightResult": {
                        "global": {
                            "name": {
                                "value": "Arise Collective Paxton",
                                "matchLevel": "none",
                                "matchedWords": []
                            },
                            "brand": {
                                "value": "Arise Collective",
                                "matchLevel": "none",
                                "matchedWords": []
                            }
                        }
                    }
                },
                {
                    "fast_ship": {
                        "fast_ship_73": 1
                    },
                    "category": {
                        "category_en": "Eyeglasses"
                    },
                    "f_material": {
                        "f_material_en": [
                            "Plastic"
                        ]
                    },
                    "s_features": {
                        "s_features_73": [
                            "Lightweight"
                        ]
                    },
                    "global": {
                        "name": "Arise Collective Pasadena",
                        "category_id": 2,
                        "brand_id": 459,
                        "brand": "Arise Collective",
                        "color_code_id": 696005,
                        "more_color_count": 2,
                        "brand_cn": "Arise Collective",
                        "lessThan8": 1,
                        "image_url": "https://image4.cdnsbg.com/2/459/696005_1733395050210.jpg",
                        "product_id": 213549
                    },
                    "url": {
                        "url_73": "/designer-eyeglasses/Arise-Collective/Arise-Collective-Pasadena-U3070-C05-696005.html"
                    },
                    "outlet": {
                        "outlet_73": 0
                    },
                    "free_lenses": {
                        "73": "1"
                    },
                    "rrp": {
                        "rrp_73": "0.00"
                    },
                    "price_for_clearance": {
                        "price_for_clearance_73": 911900
                    },
                    "bubble": {
                        "bubble_73": 0
                    },
                    "best_price_guarantee": [
                        {
                            "73": 0
                        }
                    ],
                    "s_popular": {
                        "s_popular_73": [
                            "Value Collection",
                            "In Stock",
                            "New Arrivals"
                        ]
                    },
                    "objectID": "GL696005",
                    "_highlightResult": {
                        "global": {
                            "name": {
                                "value": "Arise Collective Pasadena",
                                "matchLevel": "none",
                                "matchedWords": []
                            },
                            "brand": {
                                "value": "Arise Collective",
                                "matchLevel": "none",
                                "matchedWords": []
                            }
                        }
                    }
                },
                {
                    "fast_ship": {
                        "fast_ship_73": 1
                    },
                    "category": {
                        "category_en": "Eyeglasses"
                    },
                    "f_material": {
                        "f_material_en": [
                            "Plastic"
                        ]
                    },
                    "s_features": {
                        "s_features_73": [
                            "Lightweight"
                        ]
                    },
                    "global": {
                        "name": "Arise Collective Pasadena",
                        "category_id": 2,
                        "brand_id": 459,
                        "brand": "Arise Collective",
                        "color_code_id": 696004,
                        "more_color_count": 2,
                        "brand_cn": "Arise Collective",
                        "lessThan8": 1,
                        "image_url": "https://image4.cdnsbg.com/2/459/696004_1733395050210.jpg",
                        "product_id": 213549
                    },
                    "url": {
                        "url_73": "/designer-eyeglasses/Arise-Collective/Arise-Collective-Pasadena-U3070-C011-696004.html"
                    },
                    "outlet": {
                        "outlet_73": 0
                    },
                    "free_lenses": {
                        "73": "1"
                    },
                    "rrp": {
                        "rrp_73": "0.00"
                    },
                    "price_for_clearance": {
                        "price_for_clearance_73": 911900
                    },
                    "bubble": {
                        "bubble_73": 0
                    },
                    "best_price_guarantee": [
                        {
                            "73": 0
                        }
                    ],
                    "s_popular": {
                        "s_popular_73": [
                            "Value Collection",
                            "In Stock",
                            "New Arrivals"
                        ]
                    },
                    "objectID": "GL696004",
                    "_highlightResult": {
                        "global": {
                            "name": {
                                "value": "Arise Collective Pasadena",
                                "matchLevel": "none",
                                "matchedWords": []
                            },
                            "brand": {
                                "value": "Arise Collective",
                                "matchLevel": "none",
                                "matchedWords": []
                            }
                        }
                    }
                },
                {
                    "fast_ship": {
                        "fast_ship_73": 1
                    },
                    "category": {
                        "category_en": "Eyeglasses"
                    },
                    "f_material": {
                        "f_material_en": [
                            "Metal"
                        ]
                    },
                    "s_features": {
                        "s_features_73": [
                            "Spring Hinge",
                            "Adjustable Nose Pads",
                            "Lightweight"
                        ]
                    },
                    "global": {
                        "name": "Arise Collective Orvieto",
                        "category_id": 2,
                        "brand_id": 459,
                        "brand": "Arise Collective",
                        "color_code_id": 696003,
                        "more_color_count": 1,
                        "brand_cn": "Arise Collective",
                        "lessThan8": 3,
                        "image_url": "https://image4.cdnsbg.com/2/459/696003_1733395050206.jpg",
                        "product_id": 172224
                    },
                    "url": {
                        "url_73": "/designer-eyeglasses/Arise-Collective/Arise-Collective-Orvieto-K1173-C4-696003.html"
                    },
                    "outlet": {
                        "outlet_73": 0
                    },
                    "free_lenses": {
                        "73": "1"
                    },
                    "rrp": {
                        "rrp_73": "0.00"
                    },
                    "price_for_clearance": {
                        "price_for_clearance_73": 911900
                    },
                    "bubble": {
                        "bubble_73": 0
                    },
                    "best_price_guarantee": [
                        {
                            "73": 0
                        }
                    ],
                    "s_popular": {
                        "s_popular_73": [
                            "Value Collection",
                            "In Stock",
                            "New Arrivals"
                        ]
                    },
                    "objectID": "GL696003",
                    "_highlightResult": {
                        "global": {
                            "name": {
                                "value": "Arise Collective Orvieto",
                                "matchLevel": "none",
                                "matchedWords": []
                            },
                            "brand": {
                                "value": "Arise Collective",
                                "matchLevel": "none",
                                "matchedWords": []
                            }
                        }
                    }
                },
                {
                    "fast_ship": {
                        "fast_ship_73": 1
                    },
                    "category": {
                        "category_en": "Eyeglasses"
                    },
                    "f_material": {
                        "f_material_en": [
                            "Plastic"
                        ]
                    },
                    "s_features": {
                        "s_features_73": [
                            "Spring Hinge",
                            "Lightweight"
                        ]
                    },
                    "global": {
                        "name": "Arise Collective Maximus",
                        "category_id": 2,
                        "brand_id": 459,
                        "brand": "Arise Collective",
                        "color_code_id": 695999,
                        "more_color_count": 1,
                        "brand_cn": "Arise Collective",
                        "lessThan8": 1,
                        "image_url": "https://image4.cdnsbg.com/2/459/695999_1733395050203.jpg",
                        "product_id": 213546
                    },
                    "url": {
                        "url_73": "/designer-eyeglasses/Arise-Collective/Arise-Collective-Maximus-K1245-C2-695999.html"
                    },
                    "outlet": {
                        "outlet_73": 0
                    },
                    "free_lenses": {
                        "73": "1"
                    },
                    "rrp": {
                        "rrp_73": "0.00"
                    },
                    "price_for_clearance": {
                        "price_for_clearance_73": 911900
                    },
                    "bubble": {
                        "bubble_73": 0
                    },
                    "best_price_guarantee": [
                        {
                            "73": 0
                        }
                    ],
                    "s_popular": {
                        "s_popular_73": [
                            "Value Collection",
                            "In Stock",
                            "New Arrivals"
                        ]
                    },
                    "objectID": "GL695999",
                    "_highlightResult": {
                        "global": {
                            "name": {
                                "value": "Arise Collective Maximus",
                                "matchLevel": "none",
                                "matchedWords": []
                            },
                            "brand": {
                                "value": "Arise Collective",
                                "matchLevel": "none",
                                "matchedWords": []
                            }
                        }
                    }
                },
                {
                    "fast_ship": {
                        "fast_ship_73": 1
                    },
                    "category": {
                        "category_en": "Eyeglasses"
                    },
                    "f_material": {
                        "f_material_en": [
                            "Plastic"
                        ]
                    },
                    "s_features": {
                        "s_features_73": [
                            "Lightweight"
                        ]
                    },
                    "global": {
                        "name": "Arise Collective Marseille",
                        "category_id": 2,
                        "brand_id": 459,
                        "brand": "Arise Collective",
                        "color_code_id": 695998,
                        "more_color_count": 2,
                        "brand_cn": "Arise Collective",
                        "lessThan8": 1,
                        "image_url": "https://image4.cdnsbg.com/2/459/695998_1733395050203.jpg",
                        "product_id": 111537
                    },
                    "url": {
                        "url_73": "/designer-eyeglasses/Arise-Collective/Arise-Collective-Marseille-F1719-C2-695998.html"
                    },
                    "outlet": {
                        "outlet_73": 0
                    },
                    "free_lenses": {
                        "73": "1"
                    },
                    "rrp": {
                        "rrp_73": "0.00"
                    },
                    "price_for_clearance": {
                        "price_for_clearance_73": 911900
                    },
                    "bubble": {
                        "bubble_73": 0
                    },
                    "best_price_guarantee": [
                        {
                            "73": 0
                        }
                    ],
                    "s_popular": {
                        "s_popular_73": [
                            "Value Collection",
                            "In Stock",
                            "New Arrivals"
                        ]
                    },
                    "objectID": "GL695998",
                    "_highlightResult": {
                        "global": {
                            "name": {
                                "value": "Arise Collective Marseille",
                                "matchLevel": "none",
                                "matchedWords": []
                            },
                            "brand": {
                                "value": "Arise Collective",
                                "matchLevel": "none",
                                "matchedWords": []
                            }
                        }
                    }
                },
                {
                    "fast_ship": {
                        "fast_ship_73": 1
                    },
                    "category": {
                        "category_en": "Eyeglasses"
                    },
                    "f_material": {
                        "f_material_en": [
                            "Plastic"
                        ]
                    },
                    "s_features": {
                        "s_features_73": [
                            "Spring Hinge",
                            "Lightweight"
                        ]
                    },
                    "global": {
                        "name": "Arise Collective Mariex",
                        "category_id": 2,
                        "brand_id": 459,
                        "brand": "Arise Collective",
                        "color_code_id": 695995,
                        "more_color_count": 1,
                        "brand_cn": "Arise Collective",
                        "lessThan8": 3,
                        "image_url": "https://image4.cdnsbg.com/2/459/695995_1733395050201.jpg",
                        "product_id": 213544
                    },
                    "url": {
                        "url_73": "/designer-eyeglasses/Arise-Collective/Arise-Collective-Mariex-YC31067-C2-695995.html"
                    },
                    "outlet": {
                        "outlet_73": 0
                    },
                    "free_lenses": {
                        "73": "1"
                    },
                    "rrp": {
                        "rrp_73": "0.00"
                    },
                    "price_for_clearance": {
                        "price_for_clearance_73": 911900
                    },
                    "bubble": {
                        "bubble_73": 0
                    },
                    "best_price_guarantee": [
                        {
                            "73": 0
                        }
                    ],
                    "s_popular": {
                        "s_popular_73": [
                            "Value Collection",
                            "In Stock",
                            "New Arrivals"
                        ]
                    },
                    "objectID": "GL695995",
                    "_highlightResult": {
                        "global": {
                            "name": {
                                "value": "Arise Collective Mariex",
                                "matchLevel": "none",
                                "matchedWords": []
                            },
                            "brand": {
                                "value": "Arise Collective",
                                "matchLevel": "none",
                                "matchedWords": []
                            }
                        }
                    }
                },
                {
                    "fast_ship": {
                        "fast_ship_73": 1
                    },
                    "category": {
                        "category_en": "Eyeglasses"
                    },
                    "f_material": {
                        "f_material_en": [
                            "Plastic"
                        ]
                    },
                    "s_features": {
                        "s_features_73": [
                            "Spring Hinge",
                            "Lightweight"
                        ]
                    },
                    "global": {
                        "name": "Arise Collective Lexina",
                        "category_id": 2,
                        "brand_id": 459,
                        "brand": "Arise Collective",
                        "color_code_id": 695991,
                        "more_color_count": 1,
                        "brand_cn": "Arise Collective",
                        "lessThan8": 1,
                        "image_url": "https://image4.cdnsbg.com/2/459/695991_1733395050198.jpg",
                        "product_id": 213541
                    },
                    "url": {
                        "url_73": "/designer-eyeglasses/Arise-Collective/Arise-Collective-Lexina-FP1871-C8-695991.html"
                    },
                    "outlet": {
                        "outlet_73": 0
                    },
                    "free_lenses": {
                        "73": "1"
                    },
                    "rrp": {
                        "rrp_73": "0.00"
                    },
                    "price_for_clearance": {
                        "price_for_clearance_73": 911900
                    },
                    "bubble": {
                        "bubble_73": 0
                    },
                    "best_price_guarantee": [
                        {
                            "73": 0
                        }
                    ],
                    "s_popular": {
                        "s_popular_73": [
                            "Value Collection",
                            "In Stock",
                            "New Arrivals"
                        ]
                    },
                    "objectID": "GL695991",
                    "_highlightResult": {
                        "global": {
                            "name": {
                                "value": "Arise Collective Lexina",
                                "matchLevel": "none",
                                "matchedWords": []
                            },
                            "brand": {
                                "value": "Arise Collective",
                                "matchLevel": "none",
                                "matchedWords": []
                            }
                        }
                    }
                },
                {
                    "fast_ship": {
                        "fast_ship_73": 1
                    },
                    "category": {
                        "category_en": "Eyeglasses"
                    },
                    "f_material": {
                        "f_material_en": [
                            "Plastic"
                        ]
                    },
                    "s_features": {
                        "s_features_73": [
                            "Lightweight"
                        ]
                    },
                    "global": {
                        "name": "Arise Collective Exelle",
                        "category_id": 2,
                        "brand_id": 459,
                        "brand": "Arise Collective",
                        "color_code_id": 695985,
                        "more_color_count": 1,
                        "brand_cn": "Arise Collective",
                        "lessThan8": 1,
                        "image_url": "https://image4.cdnsbg.com/2/459/695985_1733395050193.jpg",
                        "product_id": 213536
                    },
                    "url": {
                        "url_73": "/designer-eyeglasses/Arise-Collective/Arise-Collective-Exelle-P182-C2-695985.html"
                    },
                    "outlet": {
                        "outlet_73": 0
                    },
                    "free_lenses": {
                        "73": "1"
                    },
                    "rrp": {
                        "rrp_73": "0.00"
                    },
                    "price_for_clearance": {
                        "price_for_clearance_73": 911900
                    },
                    "bubble": {
                        "bubble_73": 0
                    },
                    "best_price_guarantee": [
                        {
                            "73": 0
                        }
                    ],
                    "s_popular": {
                        "s_popular_73": [
                            "Value Collection",
                            "In Stock",
                            "New Arrivals"
                        ]
                    },
                    "objectID": "GL695985",
                    "_highlightResult": {
                        "global": {
                            "name": {
                                "value": "Arise Collective Exelle",
                                "matchLevel": "none",
                                "matchedWords": []
                            },
                            "brand": {
                                "value": "Arise Collective",
                                "matchLevel": "none",
                                "matchedWords": []
                            }
                        }
                    }
                },
                {
                    "fast_ship": {
                        "fast_ship_73": 1
                    },
                    "category": {
                        "category_en": "Eyeglasses"
                    },
                    "f_material": {
                        "f_material_en": [
                            "Metal"
                        ]
                    },
                    "s_features": {
                        "s_features_73": [
                            "Adjustable Nose Pads",
                            "Lightweight"
                        ]
                    },
                    "global": {
                        "name": "Arise Collective Exa",
                        "category_id": 2,
                        "brand_id": 459,
                        "brand": "Arise Collective",
                        "color_code_id": 695984,
                        "more_color_count": 1,
                        "brand_cn": "Arise Collective",
                        "lessThan8": 1,
                        "image_url": "https://image4.cdnsbg.com/2/459/695984_1733395050193.jpg",
                        "product_id": 213535
                    },
                    "url": {
                        "url_73": "/designer-eyeglasses/Arise-Collective/Arise-Collective-Exa-16014-C1-695984.html"
                    },
                    "outlet": {
                        "outlet_73": 0
                    },
                    "free_lenses": {
                        "73": "1"
                    },
                    "rrp": {
                        "rrp_73": "0.00"
                    },
                    "price_for_clearance": {
                        "price_for_clearance_73": 911900
                    },
                    "bubble": {
                        "bubble_73": 0
                    },
                    "best_price_guarantee": [
                        {
                            "73": 0
                        }
                    ],
                    "s_popular": {
                        "s_popular_73": [
                            "Value Collection",
                            "In Stock",
                            "New Arrivals"
                        ]
                    },
                    "objectID": "GL695984",
                    "_highlightResult": {
                        "global": {
                            "name": {
                                "value": "Arise Collective Exa",
                                "matchLevel": "none",
                                "matchedWords": []
                            },
                            "brand": {
                                "value": "Arise Collective",
                                "matchLevel": "none",
                                "matchedWords": []
                            }
                        }
                    }
                },
                {
                    "fast_ship": {
                        "fast_ship_73": 1
                    },
                    "category": {
                        "category_en": "Eyeglasses"
                    },
                    "f_material": {
                        "f_material_en": [
                            "Plastic"
                        ]
                    },
                    "s_features": {
                        "s_features_73": [
                            "Spring Hinge",
                            "Lightweight"
                        ]
                    },
                    "global": {
                        "name": "Arise Collective Dex",
                        "category_id": 2,
                        "brand_id": 459,
                        "brand": "Arise Collective",
                        "color_code_id": 695983,
                        "more_color_count": 1,
                        "brand_cn": "Arise Collective",
                        "lessThan8": 1,
                        "image_url": "https://image4.cdnsbg.com/2/459/695983_1733395050192.jpg",
                        "product_id": 213534
                    },
                    "url": {
                        "url_73": "/designer-eyeglasses/Arise-Collective/Arise-Collective-Dex-K707-C10-695983.html"
                    },
                    "outlet": {
                        "outlet_73": 0
                    },
                    "free_lenses": {
                        "73": "1"
                    },
                    "rrp": {
                        "rrp_73": "0.00"
                    },
                    "price_for_clearance": {
                        "price_for_clearance_73": 911900
                    },
                    "bubble": {
                        "bubble_73": 0
                    },
                    "best_price_guarantee": [
                        {
                            "73": 0
                        }
                    ],
                    "s_popular": {
                        "s_popular_73": [
                            "Value Collection",
                            "In Stock",
                            "New Arrivals"
                        ]
                    },
                    "objectID": "GL695983",
                    "_highlightResult": {
                        "global": {
                            "name": {
                                "value": "Arise Collective Dex",
                                "matchLevel": "none",
                                "matchedWords": []
                            },
                            "brand": {
                                "value": "Arise Collective",
                                "matchLevel": "none",
                                "matchedWords": []
                            }
                        }
                    }
                },
                {
                    "fast_ship": {
                        "fast_ship_73": 1
                    },
                    "category": {
                        "category_en": "Eyeglasses"
                    },
                    "f_material": {
                        "f_material_en": [
                            "Plastic"
                        ]
                    },
                    "s_features": {
                        "s_features_73": [
                            "Lightweight"
                        ]
                    },
                    "global": {
                        "name": "Arise Collective Brooklynn",
                        "category_id": 2,
                        "brand_id": 459,
                        "brand": "Arise Collective",
                        "color_code_id": 695981,
                        "more_color_count": 1,
                        "brand_cn": "Arise Collective",
                        "lessThan8": 1,
                        "image_url": "https://image4.cdnsbg.com/2/459/695981_1733395050189.jpg",
                        "product_id": 213532
                    },
                    "url": {
                        "url_73": "/designer-eyeglasses/Arise-Collective/Arise-Collective-Brooklynn-002-695981.html"
                    },
                    "outlet": {
                        "outlet_73": 0
                    },
                    "free_lenses": {
                        "73": "1"
                    },
                    "rrp": {
                        "rrp_73": "0.00"
                    },
                    "price_for_clearance": {
                        "price_for_clearance_73": 911900
                    },
                    "bubble": {
                        "bubble_73": 0
                    },
                    "best_price_guarantee": [
                        {
                            "73": 0
                        }
                    ],
                    "s_popular": {
                        "s_popular_73": [
                            "Value Collection",
                            "In Stock",
                            "New Arrivals"
                        ]
                    },
                    "objectID": "GL695981",
                    "_highlightResult": {
                        "global": {
                            "name": {
                                "value": "Arise Collective Brooklynn",
                                "matchLevel": "none",
                                "matchedWords": []
                            },
                            "brand": {
                                "value": "Arise Collective",
                                "matchLevel": "none",
                                "matchedWords": []
                            }
                        }
                    }
                },
                {
                    "fast_ship": {
                        "fast_ship_73": 1
                    },
                    "category": {
                        "category_en": "Eyeglasses"
                    },
                    "f_material": {
                        "f_material_en": [
                            "Plastic"
                        ]
                    },
                    "s_features": {
                        "s_features_73": [
                            "Spring Hinge",
                            "Lightweight"
                        ]
                    },
                    "global": {
                        "name": "Arise Collective Arlington",
                        "category_id": 2,
                        "brand_id": 459,
                        "brand": "Arise Collective",
                        "color_code_id": 695979,
                        "more_color_count": 1,
                        "brand_cn": "Arise Collective",
                        "lessThan8": 1,
                        "image_url": "https://image4.cdnsbg.com/2/459/695979_1733395050187.jpg",
                        "product_id": 111534
                    },
                    "url": {
                        "url_73": "/designer-eyeglasses/Arise-Collective/Arise-Collective-Arlington-F1716-C4-695979.html"
                    },
                    "outlet": {
                        "outlet_73": 0
                    },
                    "free_lenses": {
                        "73": "1"
                    },
                    "rrp": {
                        "rrp_73": "0.00"
                    },
                    "price_for_clearance": {
                        "price_for_clearance_73": 911900
                    },
                    "bubble": {
                        "bubble_73": 0
                    },
                    "best_price_guarantee": [
                        {
                            "73": 0
                        }
                    ],
                    "s_popular": {
                        "s_popular_73": [
                            "Value Collection",
                            "In Stock",
                            "New Arrivals"
                        ]
                    },
                    "objectID": "GL695979",
                    "_highlightResult": {
                        "global": {
                            "name": {
                                "value": "Arise Collective Arlington",
                                "matchLevel": "none",
                                "matchedWords": []
                            },
                            "brand": {
                                "value": "Arise Collective",
                                "matchLevel": "none",
                                "matchedWords": []
                            }
                        }
                    }
                },
                {
                    "fast_ship": {
                        "fast_ship_73": 1
                    },
                    "category": {
                        "category_en": "Eyeglasses"
                    },
                    "f_material": {
                        "f_material_en": [
                            "Plastic"
                        ]
                    },
                    "s_features": {
                        "s_features_73": [
                            "Spring Hinge",
                            "Lightweight"
                        ]
                    },
                    "global": {
                        "name": "Arise Collective Acquamarine",
                        "category_id": 2,
                        "brand_id": 459,
                        "brand": "Arise Collective",
                        "color_code_id": 695978,
                        "more_color_count": 1,
                        "brand_cn": "Arise Collective",
                        "lessThan8": 1,
                        "image_url": "https://image4.cdnsbg.com/2/459/695978_1733395050186.jpg",
                        "product_id": 172194
                    },
                    "url": {
                        "url_73": "/designer-eyeglasses/Arise-Collective/Arise-Collective-Acquamarine-F123-C33-695978.html"
                    },
                    "outlet": {
                        "outlet_73": 0
                    },
                    "free_lenses": {
                        "73": "1"
                    },
                    "rrp": {
                        "rrp_73": "0.00"
                    },
                    "price_for_clearance": {
                        "price_for_clearance_73": 911900
                    },
                    "bubble": {
                        "bubble_73": 0
                    },
                    "best_price_guarantee": [
                        {
                            "73": 0
                        }
                    ],
                    "s_popular": {
                        "s_popular_73": [
                            "Value Collection",
                            "In Stock",
                            "New Arrivals"
                        ]
                    },
                    "objectID": "GL695978",
                    "_highlightResult": {
                        "global": {
                            "name": {
                                "value": "Arise Collective Acquamarine",
                                "matchLevel": "none",
                                "matchedWords": []
                            },
                            "brand": {
                                "value": "Arise Collective",
                                "matchLevel": "none",
                                "matchedWords": []
                            }
                        }
                    }
                }
            ],
            "nbHits": 16,
            "page": 0,
            "nbPages": 1,
            "hitsPerPage": 59,
            "facets": {
                "sizes": {
                    "47": 3,
                    "53": 3,
                    "50": 2,
                    "52": 2,
                    "54": 2,
                    "44": 1,
                    "46": 1,
                    "51": 1,
                    "56": 1
                },
                "global.brand": {
                    "Arise Collective": 16
                },
                "size_category": {
                    "L": 6,
                    "M": 5,
                    "S": 5
                },
                "f_type.f_type_en": {
                    "Full Rim": 15,
                    "Rimless": 1
                },
                "gender.gender_en": {
                    "Women": 16,
                    "Men": 15
                },
                "l_type.l_type_73": {
                    "Single Vision": 16,
                    "Transitions®": 16,
                    "Multifocal/Progressive": 15
                },
                "f_color.f_color_en": {
                    "Tortoiseshell": 7,
                    "Black": 3,
                    "Gold": 2,
                    "Green": 2,
                    "Brown": 1,
                    "Clear": 1,
                    "Yellow": 1
                },
                "f_shape.f_shape_en": {
                    "Square": 7,
                    "Oval": 5,
                    "Rectangle": 3,
                    "Butterfly": 1
                },
                "category.category_en": {
                    "Eyeglasses": 16
                },
                "s_popular.s_popular_73": {
                    "In Stock": 16,
                    "New Arrivals": 16,
                    "Value Collection": 16
                },
                "f_material.f_material_en": {
                    "Plastic": 14,
                    "Metal": 2
                },
                "face_shape.face_shape_en": {
                    "Oval": 16,
                    "Round": 15,
                    "Heart": 9,
                    "Square": 6
                },
                "s_features.s_features_73": {
                    "Lightweight": 16,
                    "Spring Hinge": 9,
                    "Adjustable Nose Pads": 2
                },
                "price_for_clearance.price_for_clearance_73": {
                    "911900": 16
                }
            },
            "facets_stats": {
                "sizes": {
                    "min": 44,
                    "max": 56,
                    "avg": 50,
                    "sum": 809
                },
                "price_for_clearance.price_for_clearance_73": {
                    "min": 911900,
                    "max": 911900,
                    "avg": 911900,
                    "sum": 14590400
                }
            },
            "query": "",
            "index": "sbg",
            "queryID": "aecf2c079165137003b3b61fe37b60e9"
        },
        {
            "hits": [],
            "nbHits": 28,
            "page": 0,
            "nbPages": 0,
            "hitsPerPage": 0,
            "facets": {
                "category.category_en": {
                    "Eyeglasses": 16,
                    "Sunglasses": 12
                }
            },
            "query": "",
            "index": "sbg"
        },
        {
            "hits": [],
            "nbHits": 5044,
            "page": 0,
            "nbPages": 0,
            "hitsPerPage": 0,
            "facets": {
                "global.brand": {
                    "Swarovski": 253,
                    "VANNI": 226,
                    "Brendel": 198,
                    "Etnia Barcelona": 183,
                    "Mini": 158,
                    "Gant": 147,
                    "Police": 128,
                    "Steve McQueen": 120,
                    "Vera Wang": 119,
                    "Vogue Eyewear": 111,
                    "Ana Hickmann": 102,
                    "Mykita": 84,
                    "BOSS": 80,
                    "Sting": 80,
                    "Carrera": 79,
                    "Maje": 79,
                    "Armani Exchange": 76,
                    "Rodenstock": 76,
                    "Nike": 75,
                    "Silhouette": 75,
                    "Coach": 69,
                    "New Balance": 69,
                    "Longchamp": 68,
                    "SmartBuy Collection": 61,
                    "Michael Kors": 60,
                    "Yalea": 58,
                    "Calvin Klein": 57,
                    "Paul Smith": 57,
                    "Dolce & Gabbana": 56,
                    "Marc Jacobs": 56,
                    "Ray-Ban": 54,
                    "Skechers": 54,
                    "Versace": 54,
                    "Lozza": 53,
                    "Tom Ford": 53,
                    "Arnette": 52,
                    "Tommy Hilfiger": 52,
                    "Fila": 51,
                    "Emporio Armani": 50,
                    "Kaleos": 50,
                    "Kate Spade": 50,
                    "Blumarine": 48,
                    "Seventh Street": 48,
                    "Liu Jo": 47,
                    "Tiffany & Co.": 44,
                    "David Beckham": 43,
                    "ChangeMe!": 42,
                    "Persol": 42,
                    "Pierre Cardin": 42,
                    "Linda Farrow": 41,
                    "Giorgio Armani": 38,
                    "Timberland": 38,
                    "Moschino": 37,
                    "Levi's": 36,
                    "Max & Co.": 36,
                    "Nina Ricci": 36,
                    "Just Cavalli": 33,
                    "SmartBuy Kids": 33,
                    "Calvin Klein Jeans": 30,
                    "Zeiss": 29,
                    "Adidas Originals": 28,
                    "Lacoste": 28,
                    "Face a Face": 27,
                    "Moschino Love": 27,
                    "Rudy Project": 27,
                    "Polo Ralph Lauren": 26,
                    "Web": 25,
                    "Max Mara": 24,
                    "Kensie": 21,
                    "Miu Miu": 21,
                    "Hackett": 20,
                    "Adidas": 18,
                    "Emilio Pucci": 18,
                    "L.G.R": 17,
                    "Prada": 17,
                    "Arise Collective": 16,
                    "Philipp Plein": 16,
                    "Guess": 14,
                    "Harley Davidson": 14,
                    "Bebe": 13,
                    "Fossil": 13,
                    "Pepe Jeans": 13,
                    "Polaroid": 12,
                    "Banana Republic": 11,
                    "Burberry": 11,
                    "Jhane Barnes": 11,
                    "Ted Baker": 11,
                    "Liz Claiborne": 10,
                    "Missoni": 10,
                    "Oakley": 10,
                    "Anna-Karin Karlsson": 9,
                    "Christian Lacroix": 9,
                    "HUGO": 9,
                    "Donna Karan": 8,
                    "Nine West": 8,
                    "Under Armour": 8,
                    "Montana Readers": 7,
                    "Prada Linea Rossa": 7,
                    "Ray-Ban Kids": 7,
                    "Carolina Herrera": 6,
                    "Dsquared2": 6,
                    "Chesterfield": 5,
                    "Joseph Abboud": 5,
                    "Paradigm": 5,
                    "Privé Revaux": 5,
                    "Cole Haan": 4,
                    "Salvatore Ferragamo": 4,
                    "Adensco": 3,
                    "Elasta": 3,
                    "Miraflex": 3,
                    "Ralph Lauren": 3,
                    "Coco Song": 2,
                    "Emozioni": 2,
                    "Flexon": 2,
                    "Wiley X": 2,
                    "Alexander McQueen": 1,
                    "Furla": 1,
                    "Gunnar": 1,
                    "Messy Weekend": 1,
                    "Redele": 1,
                    "Tory Burch": 1,
                    "United Colors of Benetton": 1
                }
            },
            "query": "",
            "index": "sbg"
        }
    ]
}